{"CF40BF5D0":{"id":"CF40BF5D0","playerCount":2,"seats":[{"side":"bottom","playerId":"1247819f9c113685","name":"char","isBot":false,"connected":true},{"side":"top","playerId":null,"name":"chdd","isBot":true,"connected":true}],"hostPlayerId":"1247819f9c113685","phase":"playing","boardState":null,"lastActivityAt":1784767427818},"C4027F63D":{"id":"C4027F63D","playerCount":2,"seats":[null,null],"hostPlayerId":null,"phase":"lobby","boardState":null,"lastActivityAt":1784767254015},"C43D5AF2A":{"id":"C43D5AF2A","playerCount":2,"seats":[null,null],"hostPlayerId":null,"phase":"lobby","boardState":null,"lastActivityAt":1784767399365},"C2CCB60E6":{"id":"C2CCB60E6","playerCount":2,"seats":[{"side":"bottom","playerId":"1d342a74446f5eb4","name":"Player","isBot":false,"connected":true},{"side":"top","playerId":null,"name":"Bot A","isBot":true,"connected":true}],"hostPlayerId":"1d342a74446f5eb4","phase":"playing","boardState":null,"lastActivityAt":1784768570748},"C11E6E6B4":{"id":"C11E6E6B4","playerCount":2,"seats":[{"side":"bottom","playerId":"e28e4d3a5bb919ec","name":"brown","isBot":false,"connected":false},{"side":"top","playerId":null,"name":"Bot A","isBot":true,"connected":true}],"hostPlayerId":null,"phase":"playing","boardState":{"turnPos":1,"gameOver":false,"boardNumber":0,"scores":{"white":0,"black":0},"matchScore":{"teamA":0,"teamB":0},"queenCoveredBy":null,"skipPending":{"bottom":true},"coins":[{"x":396.02294468392404,"y":395.6453059671358,"vx":0,"vy":0,"color":"red","r":15.5,"potted":false},{"x":485.31799038973475,"y":275.91947292479415,"vx":0,"vy":0,"color":"black","r":15.5,"potted":false},{"x":427.4486250810887,"y":407.74302327784204,"vx":0,"vy":0,"color":"white","r":15.5,"potted":false},{"x":404.5470935692203,"y":437.78062202308854,"vx":0,"vy":0,"color":"black","r":15.5,"potted":false},{"x":327.85869230785215,"y":467.61490881805906,"vx":0,"vy":0,"color":"white","r":15.5,"potted":false},{"x":318.49274456582765,"y":416.20632370530103,"vx":0,"vy":0,"color":"black","r":15.5,"potted":false},{"x":378.00591337711455,"y":342.0146484916087,"vx":0,"vy":0,"color":"white","r":15.5,"potted":false},{"x":588.1739187173935,"y":161.45244096617392,"vx":0,"vy":0,"color":"white","r":15.5,"potted":false},{"x":524.2741419264237,"y":280.96454354851045,"vx":0,"vy":0,"color":"black","r":15.5,"potted":false},{"x":585.9723907869018,"y":414.20316297620093,"vx":0,"vy":0,"color":"white","r":15.5,"potted":false},{"x":484.5741033371321,"y":429.89020643203327,"vx":0,"vy":0,"color":"black","r":15.5,"potted":false},{"x":479.13157766740966,"y":546.9906550385588,"vx":0,"vy":0,"color":"white","r":15.5,"potted":false},{"x":403.0674248266382,"y":494.23998619140144,"vx":0,"vy":0,"color":"black","r":15.5,"potted":false},{"x":302.348399243062,"y":510.3709636484719,"vx":0,"vy":0,"color":"white","r":15.5,"potted":false},{"x":222.36274607523052,"y":532.9888135123143,"vx":0,"vy":0,"color":"black","r":15.5,"potted":false},{"x":162.39126159236153,"y":374.72365375327985,"vx":0,"vy":0,"color":"white","r":15.5,"potted":false},{"x":300.82178567563966,"y":366.53361543717136,"vx":0,"vy":0,"color":"black","r":15.5,"potted":false},{"x":300.7959397292065,"y":205.41237514012874,"vx":0,"vy":0,"color":"white","r":15.5,"potted":false},{"x":423.4144114017735,"y":338.91036283933255,"vx":0,"vy":0,"color":"black","r":15.5,"potted":false}],"striker":{"x":400,"y":93,"vx":0,"vy":0,"r":18.5,"potted":false},"replay":{"preShotCoins":[{"x":400,"y":400,"potted":false},{"x":400,"y":368.69,"potted":false},{"x":427.1152553924908,"y":384.345,"potted":false},{"x":427.1152553924908,"y":415.655,"potted":false},{"x":400,"y":431.31,"potted":false},{"x":372.8847446075092,"y":415.655,"potted":false},{"x":372.8847446075092,"y":384.34499999999997,"potted":false},{"x":423.1094807478276,"y":342.8020280117749,"potted":false},{"x":448.6123833899987,"y":362.01984358716015,"potted":false},{"x":461.08963716066745,"y":391.4144114017736,"potted":false},{"x":457.1979719882251,"y":423.1094807478276,"potted":false},{"x":437.98015641283985,"y":448.6123833899987,"potted":false},{"x":408.5855885982264,"y":461.08963716066745,"potted":false},{"x":376.8905192521724,"y":457.1979719882251,"potted":false},{"x":351.3876166100013,"y":437.98015641283985,"potted":false},{"x":338.91036283933255,"y":408.5855885982264,"potted":false},{"x":342.8020280117749,"y":376.8905192521724,"potted":false},{"x":362.01984358716015,"y":351.3876166100013,"potted":false},{"x":391.4144114017735,"y":338.91036283933255,"potted":false}],"startStrikerX":400,"startStrikerY":707,"vx":-4.379357714292194,"vy":-16.39645113908817,"actingPos":0}},"lastActivityAt":1784768696413}}